COPYING
MANIFEST.in
README.rst
setup.py
version.py
SimpleGUITk.egg-info/PKG-INFO
SimpleGUITk.egg-info/SOURCES.txt
SimpleGUITk.egg-info/dependency_links.txt
SimpleGUITk.egg-info/requires.txt
SimpleGUITk.egg-info/top_level.txt
simpleguitk/__init__.py
simpleguitk/canvas.py
simpleguitk/constants.py
simpleguitk/control_objects.py
simpleguitk/frame.py
simpleguitk/image.py
simpleguitk/input.py
simpleguitk/sound.py
simpleguitk/timers.py
simpleplot/__init__.py
simpleplot/plot.py